ssss/__init__.py
ssss/common/__init__.py
ssss/common/application/__init__.py
ssss/common/application/variables.py
ssss/common/fs/__init__.py
ssss/common/fs/directory.py
ssss/common/fs/file.py
ssss/common/md/__init__.py
ssss/common/md/context.py
ssss/common/md/rule.py
ssss/configuration/__init__.py
ssss/configuration/application.py
ssss/configuration/arguments.py
ssss/configuration/default.py
ssss/generate/__init__.py
ssss/generate/site.py
ssss-1.0.0.dist-info/LICENSE
ssss-1.0.0.dist-info/METADATA
ssss-1.0.0.dist-info/WHEEL
ssss-1.0.0.dist-info/entry_points.txt
ssss-1.0.0.dist-info/RECORD
