Metadata-Version: 2.1
Name: ssss
Version: 1.0.0
Summary: ssss, short for Super Simple Static Site, is a static site generator that leverages Jinja and Markdown for creating templates and content. It generates static HTML files for an efficient and lightweight website.
Author: Magnus Åberg
Author-email: himself@magnusaberg.me
Requires-Python: >=3.10,<4.0
Classifier: Programming Language :: Python :: 3
Classifier: Programming Language :: Python :: 3.10
Classifier: Programming Language :: Python :: 3.11
Requires-Dist: argparse (>=1.4.0,<2.0.0)
Requires-Dist: importlib-metadata (>=6.3.0,<7.0.0)
Requires-Dist: jinja2 (>=3.1.2,<4.0.0)
Requires-Dist: markdown (>=3.4.3,<4.0.0)
Requires-Dist: pyyaml (>=6.0,<7.0)
